together_web3/__init__.py
together_web3/accounts.py
together_web3/computer.py
together_web3/coordinator.py
together_web3/together.py
together_web3-0.1.6.dist-info/METADATA
together_web3-0.1.6.dist-info/WHEEL
together_web3-0.1.6.dist-info/RECORD
