Metadata-Version: 2.1
Name: together-web3
Version: 0.1.6
Summary: 
Home-page: https://github.com/togethercomputer/web3.py
License: MIT
Keywords: NLP,vision,speech,deep,learning,transformer,pytorch,tensorflow,BERT,GPT-2
Author: together
Author-email: together@together.xyz
Requires-Python: >=3.7.2,<3.11
Classifier: License :: OSI Approved :: MIT License
Classifier: Programming Language :: Python :: 3
Classifier: Programming Language :: Python :: 3.8
Classifier: Programming Language :: Python :: 3.9
Classifier: Programming Language :: Python :: 3.10
Requires-Dist: dacite (>=1.6.0,<2.0.0)
Requires-Dist: web3 (>=5.30.0,<6.0.0)
Project-URL: Repository, https://github.com/togethercomputer/web3.py
